resnnance/__init__.py
resnnance/core/__init__.py
resnnance/core/templates/template.vhd
resnnance/pyNN/__init__.py
resnnance/pyNN/control.py
resnnance/pyNN/populations.py
resnnance/pyNN/projections.py
resnnance/pyNN/recording.py
resnnance/pyNN/simulator.py
resnnance/pyNN/models/cells.py
resnnance/pyNN/models/synapses.py
resnnance-0.0.4.dist-info/METADATA
resnnance-0.0.4.dist-info/WHEEL
resnnance-0.0.4.dist-info/RECORD
