Metadata-Version: 2.1
Name: resnnance
Version: 0.0.4
Summary: An FPGA hardware accelerator generator for spiking neural networks + PyNN frontend
Project-URL: Homepage, https://repo-lsi.die.upm.es/slopez/resnnance
Project-URL: Bug Tracker, https://repo-lsi.die.upm.es/slopez/resnnance/issues
Author-email: Samuel López Asunción <samuel.lopez.asuncion@upm.es>
Classifier: Development Status :: 1 - Planning
Classifier: Operating System :: OS Independent
Classifier: Programming Language :: Python :: 3
Requires-Python: >=3.9
Requires-Dist: jinja2
Requires-Dist: networkx
Requires-Dist: numpy
Requires-Dist: pynn
